xia_fields_network/__init__.py
xia_fields_network/fields.cpython-310-darwin.so
xia_fields_network-0.0.7.dist-info/LICENSE.txt
xia_fields_network-0.0.7.dist-info/METADATA
xia_fields_network-0.0.7.dist-info/WHEEL
xia_fields_network-0.0.7.dist-info/top_level.txt
xia_fields_network-0.0.7.dist-info/RECORD
