Metadata-Version: 2.1
Name: xia-fields-network
Version: 0.0.7
Home-page: https://develop.x-i-a.com/docs/xia-fields-network/0.0.7/index.html
Author: X-I-A
Author-email: admin@x-i-a.com
Requires-Python: >=3.9
License-File: LICENSE.txt
Requires-Dist: xia-fields
